MANIFEST.in
README.md
setup.py
mf/__init__.py
mf/annotation.py
mf/dashboard.py
mf/db_conn.py
mf/renderer.py
mf/views.py
mf.egg-info/PKG-INFO
mf.egg-info/SOURCES.txt
mf.egg-info/dependency_links.txt
mf.egg-info/requires.txt
mf.egg-info/top_level.txt
test/testDashboard.py
test/testViews.py