Metadata-Version: 1.0
Name: mf
Version: 0.1.26
Summary: MongoKit forms generation and Pyramid Administration Dashboard
Home-page: https://github.com/mobyle2/mf-pyramid
Author: Olivier Sallou
Author-email: olivier.sallou@irisa.fr
License: LGPL
Platform: UNKNOWN
